spark_pipeline_framework/__init__.py
spark_pipeline_framework/py.typed
spark_pipeline_framework/register.py
spark_pipeline_framework/event_loggers/__init__.py
spark_pipeline_framework/event_loggers/event_logger.py
spark_pipeline_framework/event_loggers/slack_logger/__init__.py
spark_pipeline_framework/event_loggers/slack_logger/v1/__init__.py
spark_pipeline_framework/event_loggers/slack_logger/v1/slack_event_logger.py
spark_pipeline_framework/logger/__init__.py
spark_pipeline_framework/logger/log_level.py
spark_pipeline_framework/logger/yarn_logger.py
spark_pipeline_framework/mixins/__init__.py
spark_pipeline_framework/mixins/loop_id_mixin.py
spark_pipeline_framework/mixins/telemetry_parent_mixin.py
spark_pipeline_framework/pipelines/__init__.py
spark_pipeline_framework/pipelines/framework_pipeline.py
spark_pipeline_framework/pipelines/test/__init__.py
spark_pipeline_framework/pipelines/test/test_can_run_framework_pipeline.py
spark_pipeline_framework/pipelines/v2/__init__.py
spark_pipeline_framework/pipelines/v2/framework_pipeline.py
spark_pipeline_framework/pipelines/v2/test/__init__.py
spark_pipeline_framework/pipelines/v2/test/test_framework_pipeline.py
spark_pipeline_framework/progress_logger/__init__.py
spark_pipeline_framework/progress_logger/progress_log_metric.py
spark_pipeline_framework/progress_logger/progress_logger.py
spark_pipeline_framework/progress_logger/progress_logger_run.py
spark_pipeline_framework/progress_logger/test/__init__.py
spark_pipeline_framework/progress_logger/test/looping_pipeline.py
spark_pipeline_framework/progress_logger/test/mapping_pipeline.py
spark_pipeline_framework/progress_logger/test/simple_pipeline.py
spark_pipeline_framework/progress_logger/test/test_progress_logger.py
spark_pipeline_framework/progress_logger/test/test_progress_logger_async.py
spark_pipeline_framework/proxy_generator/__init__.py
spark_pipeline_framework/proxy_generator/generate_proxies.py
spark_pipeline_framework/proxy_generator/proxy_base.py
sparkpipelineframework-4.0.22.dist-info/licenses/LICENSE
sparkpipelineframework-4.0.22.dist-info/METADATA
sparkpipelineframework-4.0.22.dist-info/WHEEL
sparkpipelineframework-4.0.22.dist-info/top_level.txt
sparkpipelineframework-4.0.22.dist-info/RECORD
