Metadata-Version: 2.4
Name: sparkpipelineframework
Version: 4.0.22
Summary: Framework for simpler Spark Pipelines
Home-page: https://github.com/icanbwell/SparkPipelineFramework
Author: Imran Qureshi
Author-email: imranq2@hotmail.com
Classifier: Development Status :: 4 - Beta
Classifier: Programming Language :: Python :: 3
Classifier: License :: OSI Approved :: Apache Software License
Classifier: Operating System :: OS Independent
Requires-Python: >=3.10
License-File: LICENSE
Requires-Dist: protobuf>=3
Requires-Dist: pyspark==3.5.1
Requires-Dist: pyarrow>=17.0.0
Requires-Dist: delta-spark==3.2.0
Requires-Dist: sparkautomapper>=3.0.1
Requires-Dist: pymysql>=1.1.1
Requires-Dist: furl>=2.1.3
Requires-Dist: requests>=2.32.3
Requires-Dist: boto3>=1.34.140
Requires-Dist: chardet
Requires-Dist: slack-sdk>=3.22.0
Requires-Dist: smart-open[s3]>=6.3.0
Requires-Dist: sqlalchemy>=1.4.37
Requires-Dist: sqlparse>=0.5.3
Requires-Dist: bounded-pool-executor>=0.0.3
Requires-Dist: fastjsonschema>=2.18.0
Requires-Dist: helix.fhir.client.sdk>=4.1.11
Requires-Dist: opensearch-py[async]>=2.6.0
Requires-Dist: pyathena>2.14.0
Requires-Dist: spark-nlp>=4.2.3
Requires-Dist: pymongo>=4.10.1
Requires-Dist: pandas>=2
Requires-Dist: structlog>=23.1.0
Requires-Dist: usaddress>=0.5.10
Requires-Dist: usaddress-scourgify>=0.6.0
Requires-Dist: aiohttp>=3.10.11
Requires-Dist: pydantic>=2.8.2
Requires-Dist: motor[snappy,zstd]>=3.5.1
Requires-Dist: dataclasses-json>=0.6.7
Requires-Dist: helixtelemetry>=1.0.3
Requires-Dist: opentelemetry-api>=1.30.0
Requires-Dist: opentelemetry-sdk>=1.30.0
Requires-Dist: opentelemetry-exporter-otlp>=1.30.0
Requires-Dist: opentelemetry-instrumentation-aiohttp-client>=0.51b0
Requires-Dist: msgpack>=1.1.0
Dynamic: author
Dynamic: author-email
Dynamic: classifier
Dynamic: description
Dynamic: description-content-type
Dynamic: home-page
Dynamic: license-file
Dynamic: requires-dist
Dynamic: requires-python
Dynamic: summary
